finpy_tse/__init__.py
finpy_tse-1.2.10.dist-info/LICENSE.txt
finpy_tse-1.2.10.dist-info/METADATA
finpy_tse-1.2.10.dist-info/WHEEL
finpy_tse-1.2.10.dist-info/top_level.txt
finpy_tse-1.2.10.dist-info/RECORD
