Metadata-Version: 2.1
Name: finpy_tse
Version: 1.2.10
Summary: A Python Module to Access Tehran Stock Exchange Historical and Real-Time Data
Author: ALI RAHIMI  AND  RASOOL GHAFOURI
Author-email: a.rahimi.aut@gmail.com
License: BSD (3-clause)
License-File: LICENSE.txt
Requires-Dist: requests
Requires-Dist: jdatetime
Requires-Dist: pandas
Requires-Dist: numpy
Requires-Dist: requests
Requires-Dist: bs4
Requires-Dist: asyncio
Requires-Dist: urllib3
Requires-Dist: aiohttp
Requires-Dist: unsync
Requires-Dist: IPython
Requires-Dist: persiantools
Requires-Dist: datetime
Requires-Dist: XlsxWriter
Requires-Dist: lxml
